MANIFEST.in
setup.cfg
setup.py
docs/AUTHORS.txt
docs/LICENSE.txt
docs/README.devel
docs/README.txt
imdbpykit/__init__.py
imdbpykit/app.py
imdbpykit/sitepage.py
imdbpykit/wsgiapp.py
imdbpykit/xmladapter.py
imdbpykit.egg-info/PKG-INFO
imdbpykit.egg-info/SOURCES.txt
imdbpykit.egg-info/dependency_links.txt
imdbpykit.egg-info/entry_points.txt
imdbpykit.egg-info/not-zip-safe
imdbpykit.egg-info/requires.txt
imdbpykit.egg-info/top_level.txt
imdbpykit/conf/imdbpykit.ini.sample
imdbpykit/conf/imdbpykit.wsgi.sample
imdbpykit/conf/wsgi.conf.sample
imdbpykit/web/__init__.py
imdbpykit/web/character.py
imdbpykit/web/clear.py
imdbpykit/web/company.py
imdbpykit/web/index.py
imdbpykit/web/name.py
imdbpykit/web/search.py
imdbpykit/web/title.py
imdbpykit/web/update.py
imdbpykit/web/static/header_back.png
imdbpykit/web/static/imdbpyPowered.png
imdbpykit/web/static/imdbpyweb-translations.xml
imdbpykit/web/static/imdbpyweb.css
imdbpykit/web/static/imdbpyweb.js
imdbpykit/web/static/imdbpyweb.xsl
imdbpykit/web/static/less.png
imdbpykit/web/static/more.png
imdbpykit/web/static/cache/.DO_NOT_DELETE_THIS_FILE
imdbpykit/web/static/cache/.environment.xml