Metadata-Version: 1.0
Name: imdbpykit
Version: 1.1.1
Summary: Web interface for IMDbPY
Home-page: http://imdbpy.sourceforge.net/?page=programs#imdbpykit
Author: H. Turgut Uyar
Author-email: uyar@tekir.org
License: GPL
Keywords: imdb imdbpy paste webkit wsgi
Platform: UNKNOWN
Classifier: Development Status :: 4 - Beta
Classifier: Environment :: Web Environment
Classifier: Intended Audience :: End Users/Desktop
Classifier: License :: OSI Approved :: GNU General Public License (GPL)
Classifier: Natural Language :: English
Classifier: Programming Language :: Python
Classifier: Operating System :: OS Independent
Classifier: Topic :: Database :: Front-Ends
Classifier: Topic :: Internet :: WWW/HTTP :: Dynamic Content :: CGI Tools/Libraries
